onapy/__init__.py
onapy/detector3d.py
onapy/motion_recognizer.py
onapy/tracker2d.py
onapy/tracker3d.py
onapy/configs/camera_intrinsic.json
onapy/configs/default_runtime.py
onapy/configs/yolact_onaho.py
onapy-0.0.1.dev2.data/scripts/recognize_onaho_motion
onapy-0.0.1.dev2.data/scripts/recognize_waist_motion
onapy-0.0.1.dev2.dist-info/LICENSE
onapy-0.0.1.dev2.dist-info/METADATA
onapy-0.0.1.dev2.dist-info/WHEEL
onapy-0.0.1.dev2.dist-info/dependency_links.txt
onapy-0.0.1.dev2.dist-info/top_level.txt
onapy-0.0.1.dev2.dist-info/RECORD
