Metadata-Version: 2.1
Name: onapy
Version: 0.0.1.dev2
Summary: Onapy is the library to for next generation of masturbation.
Home-page: https://github.com/xiong-jie-y/onapy
Author: xiong jie
Author-email: fwvillage@gmail.com
License: MIT License
Keywords: perception,masturbation
Platform: UNKNOWN
Requires-Dist: opencv-python
Requires-Dist: click
Requires-Dist: open3d
Requires-Dist: numpy
Requires-Dist: scikit-spatial
Requires-Dist: cupoch
Requires-Dist: pydub
Requires-Dist: pyrealsense2
Requires-Dist: gdown
